package/__init__.py
package/module.py
ilovemadpussy9-0.1.0.dist-info/METADATA
ilovemadpussy9-0.1.0.dist-info/WHEEL
ilovemadpussy9-0.1.0.dist-info/top_level.txt
ilovemadpussy9-0.1.0.dist-info/RECORD
