Metadata-Version: 2.4
Name: ilovemadpussy9
Version: 0.1.0
Summary: wrd
Author: auth
Author-email: bisects@proton.me
Classifier: Programming Language :: Python :: 3
Classifier: License :: OSI Approved :: MIT License
Classifier: Operating System :: OS Independent
Requires-Python: >=3.6
Dynamic: author
Dynamic: author-email
Dynamic: classifier
Dynamic: description-content-type
Dynamic: requires-python
Dynamic: summary
